pointdexSel/__init__.py
pointdexSel/option.py
pointdexsel-0.0.1.dist-info/LICENSE
pointdexsel-0.0.1.dist-info/METADATA
pointdexsel-0.0.1.dist-info/WHEEL
pointdexsel-0.0.1.dist-info/top_level.txt
pointdexsel-0.0.1.dist-info/RECORD
