Metadata-Version: 2.1
Name: pointdexsel
Version: 0.0.1
Summary: A selection package
Home-page: 
